pyctx/__init__.py
pyctx/context.py
pyctx/context_data.py
pyctx/helpers.py
pyctx-0.1.10.dist-info/METADATA
pyctx-0.1.10.dist-info/WHEEL
pyctx-0.1.10.dist-info/licenses/LICENSE
pyctx-0.1.10.dist-info/RECORD
