Metadata-Version: 2.4
Name: pyctx
Version: 0.1.10
Summary: Context package to use data between function calls, use timers and log it.
Project-URL: Homepage, https://github.com/molcay/pyctx
Project-URL: Issues, https://github.com/molcay/pyctx/issues
Author-email: "M. Olcay TERCANLI" <molcay@mail.com>
License-Expression: MIT
License-File: LICENSE
Keywords: code_execution,context,ctx,log,request,request_context,timer
Classifier: License :: OSI Approved :: MIT License
Classifier: Programming Language :: Python :: 3
Classifier: Programming Language :: Python :: 3.9
Classifier: Programming Language :: Python :: 3.10
Classifier: Programming Language :: Python :: 3.11
Classifier: Programming Language :: Python :: 3.12
Classifier: Programming Language :: Python :: 3.13
Classifier: Programming Language :: Python :: 3.14
Requires-Python: >=3.10
